{
  "cities": [
    {
      "id": "591b",
      "cityName": "Sivas",
      "emoji": "🇹🇷",
      "date": "2025-01-28T14:13:59.687Z",
      "notes": "",
      "position": {
        "lat": "39.791821710036075",
        "lng": "37.19664625497462"
      }
    },
    {
      "id": "80e3",
      "cityName": "Herat",
      "emoji": "🇦🇫",
      "date": "2025-01-31T09:23:28.096Z",
      "notes": "sfgsgf",
      "position": {
        "lat": "34.36672200632866",
        "lng": "62.231037066593615"
      }
    },
    {
      "id": "cc9a",
      "cityName": "Kandahar",
      "emoji": "🇦🇫",
      "date": "2025-01-31T09:23:38.726Z",
      "notes": "",
      "position": {
        "lat": "31.602363871494603",
        "lng": "65.76895905238597"
      }
    },
    {
      "id": "e4ea",
      "cityName": "Altinyayla",
      "emoji": "🇹🇷",
      "date": "2025-01-31T09:23:55.070Z",
      "notes": "",
      "position": {
        "lat": "39.285687059968666",
        "lng": "36.792709926451934"
      }
    }
  ]
}
